knowledge_base_mcp/__init__.py
knowledge_base_mcp/main.py
knowledge_base_mcp/clients/knowledge_base.py
knowledge_base_mcp/docling/html_backend.py
knowledge_base_mcp/docling/marko_grouping_parser.py
knowledge_base_mcp/docling/md_backend.py
knowledge_base_mcp/llama_index/hierarchical_node_parsers/collapse_only_children.py
knowledge_base_mcp/llama_index/hierarchical_node_parsers/docling_hierarchical_node_parser.py
knowledge_base_mcp/llama_index/hierarchical_node_parsers/hierarchical_node_parser.py
knowledge_base_mcp/llama_index/hierarchical_node_parsers/leaf_semantic_merging.py
knowledge_base_mcp/llama_index/post_processors/__init__.py
knowledge_base_mcp/llama_index/post_processors/get_child_nodes.py
knowledge_base_mcp/llama_index/post_processors/get_parent_nodes.py
knowledge_base_mcp/llama_index/post_processors/get_sibling_nodes.py
knowledge_base_mcp/llama_index/post_processors/remove_duplicate_nodes.py
knowledge_base_mcp/llama_index/query_engine/timing_retriever_query_engine.py
knowledge_base_mcp/llama_index/readers/__init__.py
knowledge_base_mcp/llama_index/readers/directory.py
knowledge_base_mcp/llama_index/readers/github.py
knowledge_base_mcp/llama_index/readers/web.py
knowledge_base_mcp/llama_index/transformations/__init__.py
knowledge_base_mcp/llama_index/transformations/batch_embeddings.py
knowledge_base_mcp/llama_index/transformations/check_docstore.py
knowledge_base_mcp/llama_index/transformations/large_node_detector.py
knowledge_base_mcp/llama_index/transformations/metadata.py
knowledge_base_mcp/llama_index/transformations/write_to_docstore.py
knowledge_base_mcp/llama_index/utils/node_registry.py
knowledge_base_mcp/servers/__init__.py
knowledge_base_mcp/servers/base.py
knowledge_base_mcp/servers/github.py
knowledge_base_mcp/servers/manage.py
knowledge_base_mcp/servers/ingest/__init__.py
knowledge_base_mcp/servers/ingest/base.py
knowledge_base_mcp/servers/ingest/filesystem.py
knowledge_base_mcp/servers/ingest/web.py
knowledge_base_mcp-0.6.3.dist-info/METADATA
knowledge_base_mcp-0.6.3.dist-info/WHEEL
knowledge_base_mcp-0.6.3.dist-info/entry_points.txt
knowledge_base_mcp-0.6.3.dist-info/RECORD
