Metadata-Version: 2.4
Name: knowledge_base_mcp
Version: 0.6.3
Summary: Knowledge Base MCP
Requires-Python: >=3.13
Requires-Dist: aiohttp[speedups]>=3.12.13
Requires-Dist: asyncclick>=8.1.8
Requires-Dist: docling-core[chunking]>=2.37.0
Requires-Dist: docling==2.42.0
Requires-Dist: duckdb>=1.3.0
Requires-Dist: fastmcp<2.11.0
Requires-Dist: flashrank>=0.2.10
Requires-Dist: githubkit>=0.12.15
Requires-Dist: gitpython>=3.1.44
Requires-Dist: llama-index-core>=0.12.45
Requires-Dist: llama-index-embeddings-fastembed>=0.3.2
Requires-Dist: llama-index-embeddings-huggingface>=0.5.4
Requires-Dist: llama-index-node-parser-docling>=0.3.2
Requires-Dist: llama-index-postprocessor-flashrank-rerank>=0.1.0
Requires-Dist: llama-index-readers-docling>=0.3.3
Requires-Dist: llama-index-readers-github>=0.6.1
Requires-Dist: llama-index-readers-slack>=0.3.1
Requires-Dist: llama-index-storage-docstore-duckdb>=0.1.0
Requires-Dist: llama-index-storage-docstore-elasticsearch>=0.3.0
Requires-Dist: llama-index-storage-index-store-duckdb>=0.1.0
Requires-Dist: llama-index-storage-index-store-elasticsearch>=0.4.0
Requires-Dist: llama-index-storage-kvstore-duckdb>=0.1.1
Requires-Dist: llama-index-vector-stores-duckdb>=0.1.0
Requires-Dist: llama-index-vector-stores-elasticsearch>=0.4.3
Requires-Dist: llama-index>=0.12.45
Requires-Dist: mcp>=1.9.0
Requires-Dist: mistune>=3.1.3
Requires-Dist: rich>=14.0.0
Requires-Dist: sentence-transformers>=4.1.0
Requires-Dist: syrupy>=4.9.1
Requires-Dist: torch>=2.7.1
Requires-Dist: tree-sitter-language-pack>=0.8.0
Requires-Dist: tree-sitter>=0.24.0
Requires-Dist: types-lxml>=2025.3.30
